j_classify/__init__.py
j_classify/j_object.py
j_classify-1.0.0.dist-info/LICENSE
j_classify-1.0.0.dist-info/METADATA
j_classify-1.0.0.dist-info/WHEEL
j_classify-1.0.0.dist-info/top_level.txt
j_classify-1.0.0.dist-info/RECORD
