Metadata-Version: 2.1
Name: j-classify
Version: 1.0.0
Summary: Improved JSON deserialization for Python
Author-email: Gabe Reed <gabrieljreed@gmail.com>
License: MIT License
Project-URL: Homepage, https://github.com/gabrieljreed/jObject
Project-URL: Bug Tracker, https://github.com/gabrieljreed/jObject/issues
Keywords: json,deserialization,serialization,object,mapping,mapping,dict,dictionary,dataclass,dataclasses,data,class,classes,jsonobject,json-object
Requires-Python: >=3.7.0
License-File: LICENSE
